CryptoConfig/__init__.py
CryptoConfig/unique_crypto_config.py
CryptoConfigMaster-0.1.dist-info/METADATA
CryptoConfigMaster-0.1.dist-info/WHEEL
CryptoConfigMaster-0.1.dist-info/top_level.txt
CryptoConfigMaster-0.1.dist-info/RECORD
