Metadata-Version: 2.1
Name: CryptoConfigMaster
Version: 0.1
Summary: A master package for crypto configurations
Home-page: https://github.com/yourusername/CryptoConfigMaster
Author: Your Unique Name
Author-email: your.unique.email@example.com
Classifier: Programming Language :: Python :: 3
Classifier: License :: OSI Approved :: MIT License
Classifier: Operating System :: OS Independent
Requires-Python: >=3.6
